fuzzylearn/.gitignore
fuzzylearn/__init__.py
fuzzylearn/classification/__init__.py
fuzzylearn/classification/fast/fast.py
fuzzylearn/classification/fast/optimum.py
fuzzylearn/classification/fast/ray.py
fuzzylearn/examples/__init__.py
fuzzylearn/examples/classification/__init__.py
fuzzylearn/examples/classification/adult_FLAutoOptunaClassifier.py
fuzzylearn/examples/classification/adult_FLAutoOptunaRayClassifier.py
fuzzylearn/examples/classification/adult_FLClassifier.py
fuzzylearn/examples/classification/adult_FLOptunaClassifier.py
fuzzylearn/examples/classification/adult_FLOptunaRayClassifier.py
fuzzylearn/examples/classification/adult_FLRayClassifier.py
fuzzylearn/examples/classification/nparray_FLAutoOptunaClassifier.py
fuzzylearn/examples/classification/nparray_FLClassifier.py
fuzzylearn/examples/classification/nparray_FLOptunaClassifier.py
fuzzylearn/examples/regression/__init__.py
fuzzylearn/examples/regression/adult_FLAutoOptunaRayRegressor.py
fuzzylearn/examples/regression/adult_FLAutoOptunaRegressor.py
fuzzylearn/examples/regression/adult_FLOptunaRayRegressor.py
fuzzylearn/examples/regression/adult_FLOptunaRegressor.py
fuzzylearn/examples/regression/adult_FLRayRegressor.py
fuzzylearn/examples/regression/adult_FLRegressor.py
fuzzylearn/examples/regression/nparray_FLAutoOptunaRegressor.py
fuzzylearn/examples/regression/nparray_FLOptunaRegressor.py
fuzzylearn/examples/regression/nparray_FLRegressor.py
fuzzylearn/interfaces/interfaces.py
fuzzylearn/model_conf.yaml
fuzzylearn/optimization_conf.yaml
fuzzylearn/regression/__init__.py
fuzzylearn/regression/fast/fast.py
fuzzylearn/regression/fast/optimum.py
fuzzylearn/regression/fast/ray.py
fuzzylearn/util/__init__.py
fuzzylearn/util/helpers.py
fuzzylearn/util/read_data.py
fuzzylearn/version.py
fuzzylearn/visualizations/plots.py
fuzzylearn-1.2.0.dist-info/LICENSE
fuzzylearn-1.2.0.dist-info/METADATA
fuzzylearn-1.2.0.dist-info/WHEEL
fuzzylearn-1.2.0.dist-info/RECORD
