Metadata-Version: 2.1
Name: fuzzylearn
Version: 1.2.0
Summary: 
Author: drhosseinjavedani
Author-email: h.javedani@gmail.com
Requires-Python: ==3.8.5
Classifier: Programming Language :: Python :: 3
Requires-Dist: category-encoders (>=2.6.1,<3.0.0)
Requires-Dist: feature-engine (>=1.6.1,<2.0.0)
Requires-Dist: install (>=1.3.5,<2.0.0)
Requires-Dist: nox (>=2023.4.22,<2024.0.0)
Requires-Dist: numpy (>=1.24.3,<2.0.0)
Requires-Dist: optuna (>=3.2.0,<4.0.0)
Requires-Dist: pandas (>=2.0.2,<3.0.0)
Requires-Dist: pip (>=23.1.2,<24.0.0)
Requires-Dist: python-dotenv (>=1.0.0,<2.0.0)
Requires-Dist: ray (>=2.5.0,<3.0.0)
Requires-Dist: wheel (>=0.40.0,<0.41.0)
